README.txt
setup.py
Products/__init__.py
Products.CalendarListingPortlet.egg-info/PKG-INFO
Products.CalendarListingPortlet.egg-info/SOURCES.txt
Products.CalendarListingPortlet.egg-info/dependency_links.txt
Products.CalendarListingPortlet.egg-info/entry_points.txt
Products.CalendarListingPortlet.egg-info/namespace_packages.txt
Products.CalendarListingPortlet.egg-info/not-zip-safe
Products.CalendarListingPortlet.egg-info/requires.txt
Products.CalendarListingPortlet.egg-info/top_level.txt
Products/CalendarListingPortlet/__init__.py
Products/CalendarListingPortlet/calendarlistingportlet.pt
Products/CalendarListingPortlet/calendarlistingportlet.py
Products/CalendarListingPortlet/changes.txt
Products/CalendarListingPortlet/configure.zcml
Products/CalendarListingPortlet/readme.txt
Products/CalendarListingPortlet/skins.zcml
Products/CalendarListingPortlet/version.txt
Products/CalendarListingPortlet/_darcs/format
Products/CalendarListingPortlet/_darcs/index_invalid
Products/CalendarListingPortlet/_darcs/inventory
Products/CalendarListingPortlet/_darcs/tentative_pristine
Products/CalendarListingPortlet/_darcs/patches/20090113174119-422b6-5c085c05bfeacc22f30b1084402290c3539a352c.gz
Products/CalendarListingPortlet/_darcs/patches/20090118170532-422b6-d57f9e3d543442a06883d4f00f54598ece36a9ec.gz
Products/CalendarListingPortlet/_darcs/patches/20120119103454-422b6-b9b4c289a1e35003159be768067557dcb22ccf50.gz
Products/CalendarListingPortlet/_darcs/patches/20120119112018-422b6-d68e7e81374066566f7a0864e5bb41b996ac0df3.gz
Products/CalendarListingPortlet/_darcs/patches/pending
Products/CalendarListingPortlet/_darcs/patches/pending.tentative
Products/CalendarListingPortlet/_darcs/prefs/author
Products/CalendarListingPortlet/_darcs/prefs/binaries
Products/CalendarListingPortlet/_darcs/prefs/boring
Products/CalendarListingPortlet/_darcs/prefs/defaultrepo
Products/CalendarListingPortlet/_darcs/prefs/motd
Products/CalendarListingPortlet/_darcs/prefs/repos
Products/CalendarListingPortlet/_darcs/pristine/__init__.py
Products/CalendarListingPortlet/_darcs/pristine/calendarlistingportlet.pt
Products/CalendarListingPortlet/_darcs/pristine/calendarlistingportlet.py
Products/CalendarListingPortlet/_darcs/pristine/configure.zcml
Products/CalendarListingPortlet/_darcs/pristine/skins.zcml
Products/CalendarListingPortlet/_darcs/pristine/version.txt
Products/CalendarListingPortlet/_darcs/pristine/i18n/calendarlistingportlet-no.mo
