Metadata-Version: 1.0
Name: Products.CalendarListingPortlet
Version: 1.0.2b
Summary: List events published for intranet
Home-page: http://www.nidelven-it.no/d
Author: Nidelven IT
Author-email: info@nidelven-it.no
License: GPL
Keywords: python plone calendar presentation portlet
Platform: UNKNOWN
Classifier: Programming Language :: Python
Classifier: Framework :: Plone
Classifier: Intended Audience :: End Users/Desktop
Classifier: Operating System :: OS Independent
Classifier: Topic :: Office/Business :: Groupware
